gb_chat/__about__.py
gb_chat/__init__.py
gb_chat/client_run.py
gb_chat/metaclass.py
gb_chat/multi_launcher.py
gb_chat/server_run.py
gb_chat/client/__init__.py
gb_chat/client/logger.py
gb_chat/client/gui/__init__.py
gb_chat/client/gui/windows/__init__.py
gb_chat/client/gui/windows/chat.py
gb_chat/client/gui/windows/login.py
gb_chat/client/gui/windows/main.py
gb_chat/server/__init__.py
gb_chat/server/contacts.py
gb_chat/server/logger.py
gb_chat/server/gui/__init__.py
gb_chat/server/gui/windows/__init__.py
gb_chat/server/gui/windows/history.py
gb_chat/server/gui/windows/main.py
gb_chat/server/gui/windows/setting.py
gb_chat/storage/__init__.py
gb_chat/storage/client/__init__.py
gb_chat/storage/client/contacts.py
gb_chat/storage/client/messages.py
gb_chat/storage/server/__init__.py
gb_chat/storage/server/client.py
gb_chat/storage/server/contacts.py
gb_chat/storage/server/history.py
gb_chat/tools/__init__.py
gb_chat/tools/config.py
gb_chat/tools/descriptors.py
gb_chat/tools/file.py
gb_chat/tools/hash.py
gb_chat/tools/requests.py
gb_chat/tools/responses.py
gb_chat/tools/validator.py
qasdet_chat-2.0.0.data/data/config.json
qasdet_chat-2.0.0.dist-info/METADATA
qasdet_chat-2.0.0.dist-info/WHEEL
qasdet_chat-2.0.0.dist-info/entry_points.txt
qasdet_chat-2.0.0.dist-info/top_level.txt
qasdet_chat-2.0.0.dist-info/RECORD
