Metadata-Version: 2.1
Name: qasdet-chat
Version: 2.0.0
Summary: Chat server and client for chating
Home-page: UNKNOWN
Author: Alexander
Author-email: qa-admin@sknt.ru
License: UNKNOWN
Platform: UNKNOWN
Requires-Dist: PyQt5 (~=5.15.9)
Requires-Dist: PyYAML (~=6.0)
Requires-Dist: chardet (~=5.1.0)
Requires-Dist: jsonschema (~=4.17.3)
Requires-Dist: peewee (~=3.16.0)
